featureforge
featureforge/experimentation
