Metadata-Version: 1.1
Name: featureforge
Version: 0.1.6
Summary: A library to build and test machine learning features
Home-page: https://github.com/machinalis/featureforge
Author: Rafael Carrascosa, Daniel Moisset, Javier Mansilla
Author-email: rcarrascosa@machinalis.com
License: UNKNOWN
Keywords: machine learning,scikit,scikit-learn,sklearn,features,testing,vectorization,preprocessing
Platform: UNKNOWN
Classifier: Programming Language :: Python
Classifier: Programming Language :: Python :: 2
Classifier: Programming Language :: Python :: 2.7
Classifier: Programming Language :: Python :: 3
Classifier: Programming Language :: Python :: 3.3
Classifier: Intended Audience :: Developers
Classifier: Development Status :: 4 - Beta
Classifier: License :: OSI Approved :: BSD License
Classifier: Operating System :: OS Independent
Classifier: Topic :: Scientific/Engineering
Classifier: Topic :: Scientific/Engineering :: Artificial Intelligence
Classifier: Topic :: Software Development :: Libraries
Classifier: Topic :: Software Development :: Testing
